pronom_cron/pronom_cron.py
pronom_export/.gitignore
pronom_export/__init__.py
pronom_export/pronom_xml_export.py
pronom_stats/pronom_stats.py
pronom_stats/db/.gitignore
pronom_summary/.gitignore
pronom_summary/__init__.py
pronom_summary/pronom_summary.py
pronom_tools/__init__.py
pronom_tools/pronom_tools.py
pronom_tools/version.py
pronom_tools-1.2.0.dist-info/LICENSE.txt
pronom_tools-1.2.0.dist-info/METADATA
pronom_tools-1.2.0.dist-info/WHEEL
pronom_tools-1.2.0.dist-info/entry_points.txt
pronom_tools-1.2.0.dist-info/top_level.txt
pronom_tools-1.2.0.dist-info/RECORD
