Metadata-Version: 2.1
Name: pronom-tools
Version: 1.2.0
Summary: Tools for working with PRONOM releases
Author-email: "R. Spencer" <all.along.the.watchtower2001+github@gmail.com>
License: GNU GENERAL PUBLIC LICENSE
Project-URL: Homepage, https://ffdev.info/
Project-URL: Bug Reports, https://github.com/ffdev-info/pronom-release-tools/issues/
Project-URL: Source, https://github.com/ffdev-info/pronom-release-tools/
Keywords: pronom,digipres,file-formats
Requires-Python: >=3.9
License-File: LICENSE.txt
Requires-Dist: python-dotenv==1.0.1
Requires-Dist: fastapi==0.109.0
Requires-Dist: passlib==1.7.4
Requires-Dist: requests==2.31.0
Requires-Dist: tenacity==8.2.3
Requires-Dist: uvicorn==0.27.0
